.gitignore
LICENSE
MANIFEST.in
README.md
requirements.txt
rltest_commands.py
setup.cfg
setup.py
test_commands.py
.circleci/config.yml
redisbloom/__init__.py
redisbloom/client.py
redisbloom.egg-info/PKG-INFO
redisbloom.egg-info/SOURCES.txt
redisbloom.egg-info/dependency_links.txt
redisbloom.egg-info/requires.txt
redisbloom.egg-info/top_level.txt