Metadata-Version: 2.1
Name: redisbloom
Version: 0.4.0
Summary: RedisBloom Python Client
Home-page: https://github.com/redislabs/redisbloom-py
Author: RedisLabs
Author-email: oss@redislabs.com
License: UNKNOWN
Keywords: R,e,d,i,s, ,E,x,t,e,n,s,i,o,n, ,P,r,o,b,a,b,i,l,i,s,t,i,c, ,T,o,p,K, ,C,u,c,k,o,o,-,F,i,l,t,e,r, ,B,l,o,o,m,-,F,i,l,t,e,r, ,C,o,u,n,t,-,m,i,n,-,s,k,e,t,c,h
Platform: UNKNOWN
Classifier: Intended Audience :: Developers
Classifier: License :: OSI Approved :: BSD License
Classifier: Programming Language :: Python :: 2.7
Classifier: Topic :: Database
